ecom_edwinlan/__about__.py
ecom_edwinlan/__init__.py
ecom_edwinlan/models.py
ecom_edwinlan/sdk.py
ecom_edwinlan-0.0.2.dist-info/METADATA
ecom_edwinlan-0.0.2.dist-info/WHEEL
ecom_edwinlan-0.0.2.dist-info/licenses/LICENSE.txt
ecom_edwinlan-0.0.2.dist-info/RECORD
