Metadata-Version: 2.4
Name: ecom-edwinlan
Version: 0.0.2
Summary: Test
Project-URL: Documentation, https://github.com/edwinlan/ecom-edwinlan#readme
Project-URL: Issues, https://github.com/edwinlan/ecom-edwinlan/issues
Project-URL: Source, https://github.com/edwinlan/ecom-edwinlan
Author-email: edwinlan <edwinlan@tencent.com>
License-Expression: MIT
License-File: LICENSE.txt
Classifier: Development Status :: 4 - Beta
Classifier: Programming Language :: Python
Classifier: Programming Language :: Python :: 3.8
Classifier: Programming Language :: Python :: 3.9
Classifier: Programming Language :: Python :: 3.10
Classifier: Programming Language :: Python :: 3.11
Classifier: Programming Language :: Python :: 3.12
Classifier: Programming Language :: Python :: Implementation :: CPython
Classifier: Programming Language :: Python :: Implementation :: PyPy
Requires-Python: >=3.8
Requires-Dist: pydantic
Requires-Dist: requests
Requires-Dist: responses
